ez50/__init__.py
ez50/commands.py
ez50/data.json
ez50/main.py
ez50/options.py
ez50/utils.py
ez50-0.1.4.dist-info/licenses/LICENSE
ez50-0.1.4.dist-info/METADATA
ez50-0.1.4.dist-info/WHEEL
ez50-0.1.4.dist-info/entry_points.txt
ez50-0.1.4.dist-info/top_level.txt
ez50-0.1.4.dist-info/RECORD
