Metadata-Version: 2.4
Name: ez50
Version: 0.1.4
Summary: CS50 made easy! Unofficial community tool and is NOT affiliated with Harvard University or CS50.
Author-email: Emerson Proenca <emersonproenca0@gmail.com>
License: MIT
Project-URL: Changelog, https://github.com/emerson-proenca/ez50/releases
Project-URL: Homepage, https://github.com/emerson-proenca/ez50
Project-URL: Issues, https://github.com/emerson-proenca/ez50/issues
Project-URL: Repository, https://github.com/emerson-proenca/ez50.git
Keywords: automation,cli,cs50,education,harvard
Classifier: Development Status :: 5 - Production/Stable
Classifier: Intended Audience :: Education
Classifier: License :: OSI Approved :: MIT License
Classifier: Operating System :: OS Independent
Classifier: Programming Language :: Python :: 3 :: Only
Classifier: Programming Language :: Python :: 3.9
Classifier: Programming Language :: Python :: 3.10
Classifier: Programming Language :: Python :: 3.11
Classifier: Programming Language :: Python :: 3.12
Classifier: Programming Language :: Python :: 3.13
Classifier: Programming Language :: Python :: 3.14
Classifier: Topic :: Education
Requires-Python: >=3.9
License-File: LICENSE
Requires-Dist: typer[all]>=0.9
Dynamic: license-file
